channels_zmq/__init__.py
channels_zmq/core.py
channels_zmq/management/commands/queue_service.py
channels_zmq-0.1.0.dist-info/LICENSE.txt
channels_zmq-0.1.0.dist-info/METADATA
channels_zmq-0.1.0.dist-info/WHEEL
channels_zmq-0.1.0.dist-info/top_level.txt
channels_zmq-0.1.0.dist-info/RECORD
