Metadata-Version: 2.1
Name: channels-zmq
Version: 0.1.0
Summary: A channel layer based on ZMQ
Home-page: https://github.com/franciscoda/channels_zmq/
Author: Francisco Altoe
License: GPLv3
Platform: any
Classifier: Development Status :: 4 - Beta
Classifier: Programming Language :: Python
License-File: LICENSE.txt
Requires-Dist: pyzmq (>=23.2.1)
Requires-Dist: channels
Requires-Dist: importlib-metadata ; python_version < "3.8"
Provides-Extra: testing
Requires-Dist: setuptools ; extra == 'testing'
Requires-Dist: pytest ; extra == 'testing'
Requires-Dist: pytest-cov ; extra == 'testing'
Requires-Dist: pytest-django ; extra == 'testing'
Requires-Dist: pytest-asyncio ; extra == 'testing'
